{
 "type": "PowerTurret",
 "name": "Башня с дробовиком",
  "placeSound": "place-2",
  "placePitchChange": false,
  "destroySound": "destroy-small",
 "description": "Андрей чмо не нарисовал башню, довольствуйтесь турелью",
 "targetAir": true,
 "targetGround": true,
 "health": 1500,
 "size": 3,
 "buildCostMultiplier": 0.2,
 "buildCost": 5,
 "inaccuracy": 8,
 "ammoPerShot": 0,
 "reload": 50,
 "recoil": 3,
 "rotateSpeed": 5,
 "shoots": 1,
 "shotWith": 1,
 "range": 120,
 "maxAmmo":50,
 "shoot": {
	 "shotDelay": 0,
	 "shots": 9
 }
 "shootType": { 
    "type": "BasicBulletType",
	"height": 20,
	"width": 7,
    "damage": 25,
    "lifetime": 30,
    "speed": 8,
	"lightColor": "fff8e8",
    "lightOpacity": 0.7,
    "lightRadius": 24.5,
    "trailColor": "f9c27a",
    "trailLength": 12,
    "trailWidth": 3,
	"despawnEffect": "none",
 },
 "requirements": [
     {"item": "camerite", "amount": 1800},
	 {"item": "camerite-refined", "amount": 500}
     ],
     "shootSound": "t_spas12_shot",
     "category": "turret",
     "alwaysUnlocked": true,
     "hasItems": true
}